docs/__init__.py
docs/conf.py
multi_job/__init__.py
multi_job/main.py
multi_job/__pycache__/__init__.cpython-36.pyc
multi_job/__pycache__/main.cpython-36.pyc
multi_job/common/__init__.py
multi_job/common/build.py
multi_job/common/clean.py
multi_job/common/deploy.py
multi_job/common/multi_stage_build.py
multi_job/common/pypi_upload.py
multi_job/common/yenv.py
multi_job/common/__pycache__/__init__.cpython-36.pyc
multi_job/docs/conf.py
multi_job/docs/modules.rst
multi_job/docs/multi_job.common.dev_actions.rst
multi_job/docs/multi_job.common.prod_actions.rst
multi_job/docs/multi_job.common.rst
multi_job/docs/multi_job.interface.rst
multi_job/docs/multi_job.models.rst
multi_job/docs/multi_job.rst
multi_job/docs/multi_job.runtime.rst
multi_job/docs/multi_job.tests.rst
multi_job/docs/multi_job.utils.rst
multi_job/docs/multi_job.validation.rst
multi_job/interface/__init__.py
multi_job/interface/formatters.py
multi_job/interface/interface.py
multi_job/interface/__pycache__/__init__.cpython-36.pyc
multi_job/interface/__pycache__/__init__.cpython-38.pyc
multi_job/interface/__pycache__/cli.cpython-36.pyc
multi_job/interface/__pycache__/colours.cpython-38.pyc
multi_job/interface/__pycache__/exceptions.cpython-36.pyc
multi_job/interface/__pycache__/formatters.cpython-36.pyc
multi_job/interface/__pycache__/formatters.cpython-38.pyc
multi_job/interface/__pycache__/interceptors.cpython-36.pyc
multi_job/interface/__pycache__/interceptors.cpython-38.pyc
multi_job/interface/__pycache__/interface.cpython-36.pyc
multi_job/interface/__pycache__/interface.cpython-38.pyc
multi_job/interface/__pycache__/models.cpython-36.pyc
multi_job/interface/__pycache__/output.cpython-36.pyc
multi_job/interface/__pycache__/parse.cpython-36.pyc
multi_job/interface/__pycache__/runner.cpython-36.pyc
multi_job/interface/__pycache__/utils.cpython-36.pyc
multi_job/models/__init__.py
multi_job/models/exceptions.py
multi_job/models/jobs.py
multi_job/models/processes.py
multi_job/models/projects.py
multi_job-0.10.13.dist-info/LICENSE.md
multi_job-0.10.13.dist-info/METADATA
multi_job-0.10.13.dist-info/WHEEL
multi_job-0.10.13.dist-info/entry_points.txt
multi_job-0.10.13.dist-info/top_level.txt
multi_job-0.10.13.dist-info/RECORD
