Metadata-Version: 2.1
Name: multi-job
Version: 0.10.13
Summary: Job runner for multifaceted projects
Home-page: https://github.com/JoelLefkowitz/multi-job
Author: Joel Lefkowitz
Author-email: joellefkowitz@hotmail.com
License: MIT
Platform: UNKNOWN
Requires-Python: >= 3.6
Requires-Dist: art (>=4.5)
Requires-Dist: dataclasses (>=0.7)
Requires-Dist: docopt (>=0.6.2)
Requires-Dist: emoji (>=0.5.4)
Requires-Dist: ruamel.yaml (>=0.16.10)
